objutils/__init__.py
objutils/ash.py
objutils/binfile.py
objutils/checksums.py
objutils/cosmac.py
objutils/emon52.py
objutils/etek.py
objutils/exceptions.py
objutils/fpc.py
objutils/hexdump.py
objutils/hexfile.py
objutils/ieee695.py
objutils/ihex.py
objutils/image.py
objutils/logger.py
objutils/mostec.py
objutils/pickleif.py
objutils/rca.py
objutils/readers.py
objutils/registry.py
objutils/section.py
objutils/shf.py
objutils/sig.py
objutils/srec.py
objutils/tek.py
objutils/titxt.py
objutils/version.py
objutils/dwarf/__init__.py
objutils/dwarf/constants.py
objutils/dwarf/encoding.py
objutils/elf/__init__.py
objutils/elf/defs.py
objutils/elf/model.py
objutils/elf/arm/__init__.py
objutils/elf/arm/attributes.py
objutils/tests/__init__.py
objutils/tests/test_arm_attributes.py
objutils/tests/test_ash.py
objutils/tests/test_checksums.py
objutils/tests/test_cygpath.py
objutils/tests/test_diff_bin.py
objutils/tests/test_emon52.py
objutils/tests/test_fpc.py
objutils/tests/test_hexdump.py
objutils/tests/test_hexfile.py
objutils/tests/test_ihex.py
objutils/tests/test_image.py
objutils/tests/test_mostec.py
objutils/tests/test_readers.py
objutils/tests/test_registry.py
objutils/tests/test_repr.py
objutils/tests/test_section.py
objutils/tests/test_shf.py
objutils/tests/test_srec.py
objutils/tests/test_tek.py
objutils/tests/test_titext.py
objutils/utils/__init__.py
objutils/utils/diff.py
objutils-0.4.12.dist-info/LICENSE
objutils-0.4.12.dist-info/METADATA
objutils-0.4.12.dist-info/WHEEL
objutils-0.4.12.dist-info/entry_points.txt
objutils-0.4.12.dist-info/top_level.txt
objutils-0.4.12.dist-info/RECORD
