Metadata-Version: 2.1
Name: objutils
Version: 0.4.12
Summary: Objectfile library for Python
Home-page: http://github.com/christoph2/objutils
Author: Christoph Schueler
Author-email: cpu12.gems@googlemail.com
License: GPLv2
Keywords: hex files,intel hex,s19,srec,srecords,object files,map files,embedded,microcontroller,ECU,shf,rfc4194
Platform: UNKNOWN
Classifier: Development Status :: 4 - Beta
Classifier: Intended Audience :: Developers
Classifier: Topic :: Software Development
Classifier: Topic :: Scientific/Engineering
Classifier: License :: OSI Approved :: GNU General Public License v2 (GPLv2)
Classifier: Programming Language :: Python :: 3.4
Classifier: Programming Language :: Python :: 3.5
Classifier: Programming Language :: Python :: 3.6
Classifier: Programming Language :: Python :: 3.7
Provides: objutils
License-File: LICENSE
Requires-Dist: future
Requires-Dist: mako
Requires-Dist: six
Requires-Dist: construct
Requires-Dist: attrs (>=19.3.0)
Requires-Dist: sortedcontainers
Requires-Dist: SQLAlchemy
Provides-Extra: develop
Requires-Dist: bumpversion ; extra == 'develop'
Provides-Extra: docs
Requires-Dist: sphinxcontrib-napoleon ; extra == 'docs'
